stochtest/.gitignore
stochtest/__about__.py
stochtest/__init__.py
stochtest/_core.py
stochtest/distributions/__init__.py
stochtest/distributions/_core.py
stochtest-0.6.2.dist-info/METADATA
stochtest-0.6.2.dist-info/WHEEL
stochtest-0.6.2.dist-info/licenses/LICENSE.txt
stochtest-0.6.2.dist-info/RECORD
