Metadata-Version: 2.4
Name: stochtest
Version: 0.6.2
Summary: Stochtest is a Python library for performing statistical assertions on stochastic outputs.
Project-URL: Repository, https://github.com/MicahBrun/stochtest
Project-URL: Issues, https://github.com/MicahBrun/stochtest/issues
Author-email: Micah Brown <micahbrun.dev@gmail.com>
License-Expression: MIT
License-File: LICENSE.txt
Keywords: MCMC,assertions,monte carlo,simulation,statistics,stochastic,test,testing,unittest
Classifier: Development Status :: 4 - Beta
Classifier: Programming Language :: Python
Classifier: Programming Language :: Python :: 3.10
Classifier: Programming Language :: Python :: 3.11
Classifier: Programming Language :: Python :: 3.12
Classifier: Programming Language :: Python :: Implementation :: CPython
Classifier: Programming Language :: Python :: Implementation :: PyPy
Requires-Python: >=3.10
Requires-Dist: numpy
Requires-Dist: scipy
